README.rst
setup.py
SQLAlchemyViz.egg-info/PKG-INFO
SQLAlchemyViz.egg-info/SOURCES.txt
SQLAlchemyViz.egg-info/dependency_links.txt
SQLAlchemyViz.egg-info/entry_points.txt
SQLAlchemyViz.egg-info/requires.txt
SQLAlchemyViz.egg-info/top_level.txt
sqlalchemyviz/__init__.py
sqlalchemyviz/cli.py
sqlalchemyviz/viz.py