Metadata-Version: 1.1
Name: SQLAlchemyViz
Version: 0.1
Summary: Package to create ER diagrams from SQLAlchemy schemas using Graphviz.
Home-page: UNKNOWN
Author: Sebastian Eckweiler
Author-email: seb.eckweiler@gmail.com
License: MIT
Platform: UNKNOWN
Classifier: Development Status :: 3 - Alpha
Classifier: Topic :: Utilities
Classifier: Topic :: Database
Classifier: Topic :: Documentation
Classifier: License :: OSI Approved :: MIT License
Classifier: Natural Language :: English
Classifier: Programming Language :: Python
